batplot/__init__.py
batplot/args.py
batplot/batch.py
batplot/batplot.py
batplot/cif.py
batplot/cli.py
batplot/color_utils.py
batplot/config.py
batplot/converters.py
batplot/cpc_interactive.py
batplot/electrochem_interactive.py
batplot/interactive.py
batplot/manual.py
batplot/modes.py
batplot/operando.py
batplot/operando_ec_interactive.py
batplot/plotting.py
batplot/readers.py
batplot/session.py
batplot/style.py
batplot/ui.py
batplot/utils.py
batplot/version_check.py
batplot/data/USER_MANUAL.md
batplot-1.8.4.dist-info/licenses/LICENSE
batplot_backup_20251121_223043/__init__.py
batplot_backup_20251121_223043/args.py
batplot_backup_20251121_223043/batch.py
batplot_backup_20251121_223043/batplot.py
batplot_backup_20251121_223043/cif.py
batplot_backup_20251121_223043/cli.py
batplot_backup_20251121_223043/color_utils.py
batplot_backup_20251121_223043/config.py
batplot_backup_20251121_223043/converters.py
batplot_backup_20251121_223043/cpc_interactive.py
batplot_backup_20251121_223043/electrochem_interactive.py
batplot_backup_20251121_223043/interactive.py
batplot_backup_20251121_223043/modes.py
batplot_backup_20251121_223043/operando.py
batplot_backup_20251121_223043/operando_ec_interactive.py
batplot_backup_20251121_223043/plotting.py
batplot_backup_20251121_223043/readers.py
batplot_backup_20251121_223043/session.py
batplot_backup_20251121_223043/style.py
batplot_backup_20251121_223043/ui.py
batplot_backup_20251121_223043/utils.py
batplot_backup_20251121_223043/version_check.py
batplot_backup_20251221_101150/__init__.py
batplot_backup_20251221_101150/args.py
batplot_backup_20251221_101150/batch.py
batplot_backup_20251221_101150/batplot.py
batplot_backup_20251221_101150/cif.py
batplot_backup_20251221_101150/cli.py
batplot_backup_20251221_101150/color_utils.py
batplot_backup_20251221_101150/config.py
batplot_backup_20251221_101150/converters.py
batplot_backup_20251221_101150/cpc_interactive.py
batplot_backup_20251221_101150/electrochem_interactive.py
batplot_backup_20251221_101150/interactive.py
batplot-1.8.4.dist-info/METADATA
batplot-1.8.4.dist-info/WHEEL
batplot-1.8.4.dist-info/entry_points.txt
batplot-1.8.4.dist-info/top_level.txt
batplot-1.8.4.dist-info/RECORD
