Metadata-Version: 2.4
Name: batplot
Version: 1.8.4
Summary: Interactive plotting tool for material science (1D plot) and electrochemistry (GC, CV, dQ/dV, CPC, operando) with batch processing
Author-email: Tian Dai <tianda@uio.no>
License: MIT License
Project-URL: Homepage, https://github.com/TianDai1729/batplot
Project-URL: Repository, https://github.com/TianDai1729/batplot
Project-URL: Issues, https://github.com/TianDai1729/batplot/issues
Classifier: Programming Language :: Python
Classifier: Programming Language :: Python :: 3
Classifier: Programming Language :: Python :: 3 :: Only
Classifier: Programming Language :: Python :: 3.13
Classifier: Operating System :: OS Independent
Classifier: Intended Audience :: Science/Research
Classifier: Topic :: Scientific/Engineering :: Visualization
Requires-Python: <3.14,>=3.13
License-File: LICENSE
Requires-Dist: numpy==2.3.4
Requires-Dist: matplotlib==3.10.7
Requires-Dist: rich>=10.0.0
Requires-Dist: openpyxl>=3.0.0
Dynamic: license-file
